CHANGES.rst
DESCRIPTION.rst
LICENSE
MANIFEST.in
README.md
setup.py
src/wai.annotations.subdir.egg-info/PKG-INFO
src/wai.annotations.subdir.egg-info/SOURCES.txt
src/wai.annotations.subdir.egg-info/dependency_links.txt
src/wai.annotations.subdir.egg-info/entry_points.txt
src/wai.annotations.subdir.egg-info/namespace_packages.txt
src/wai.annotations.subdir.egg-info/requires.txt
src/wai.annotations.subdir.egg-info/top_level.txt
src/wai/annotations/subdir/__init__.py
src/wai/annotations/subdir/ac/__init__.py
src/wai/annotations/subdir/ac/specifier/_SubDirInputFormatSpecifier.py
src/wai/annotations/subdir/ac/specifier/_SubDirOutputFormatSpecifier.py
src/wai/annotations/subdir/ac/specifier/__init__.py
src/wai/annotations/subdir/common/__init__.py
src/wai/annotations/subdir/common/component/_SubDirReader.py
src/wai/annotations/subdir/common/component/_SubDirWriter.py
src/wai/annotations/subdir/common/component/__init__.py
src/wai/annotations/subdir/common/specifier/_SubDirInputFormatSpecifier.py
src/wai/annotations/subdir/common/specifier/_SubDirOutputFormatSpecifier.py
src/wai/annotations/subdir/common/specifier/__init__.py
src/wai/annotations/subdir/ic/__init__.py
src/wai/annotations/subdir/ic/specifier/_SubDirInputFormatSpecifier.py
src/wai/annotations/subdir/ic/specifier/_SubDirOutputFormatSpecifier.py
src/wai/annotations/subdir/ic/specifier/__init__.py
src/wai/annotations/subdir/sc/__init__.py
src/wai/annotations/subdir/sc/specifier/_SubDirInputFormatSpecifier.py
src/wai/annotations/subdir/sc/specifier/_SubDirOutputFormatSpecifier.py
src/wai/annotations/subdir/sc/specifier/__init__.py